[
    /* traits:
        calm
        hardy
        jolly
        neutral
        quirky
        rash
    */

    {
        "text": "It's New Years Day, and you've decided to make a resolution to lose weight. How does it go?",
        "options": [
            {
                "option": "Give up in the first few days, it's too hard.",
                "trait": "rash",
                "value": 1
            },
            {
                "option": "Try harder but ultimately fail because of lack of motivation",
                "trait": "rash",
                "value": 1
            },
            {
                "option": "Succeed until the end, because that's how you roll!",
                "trait": "hardy",
                "value": 1
            }
        ]
    },
    {
        "text": "What kind of pet do you like?",
        "options": [
            {
                "option": "Cats! Meow.",
                "trait": "quirky",
                "value": 2
            },
            {
                "option": "Dogs are where it's at!",
                "trait": "jolly",
                "value": 1
            },
            {
                "option": "A fish lasts a lifetime.",
                "trait": "calm",
                "value": 1
            }
        ]
    },
    {
        "text": "You are in the last mile of a marathon, what do you do?",
        "options": [
            {
                "option": "Dance to taunt the people behind you!",
                "trait": "jolly",
                "value": 1
            },
            {
                "option": "Power forward!",
                "trait": "hardy",
                "value": 2
            },
            {
                "option": "Take it slow and steady to conserve energy.",
                "trait": "calm",
                "value": 1
            }
        ]
    },
    {
        "text": "What kind of grades do you get in school?",
        "options": [
            {
                "option": "Who needs grades?",
                "trait": "quirky",
                "value": 1
            },
            {
                "option": "You don't need to know.",
                "trait": "hardy",
                "value": 1
            },
            {
                "option": "Fs because I skip class every day.",
                "trait": "rash",
                "value": 1
            }
        ]
    },
    {
        "text": "You see a bunch of instruments on the ground, which one do you take?",
        "options": [
            {
                "option": "Electric guitar.",
                "trait": "rash",
                "value": 1
            },
            {
                "option": "Indian drums.",
                "trait": "quirky",
                "value": 1
            },
            {
                "option": "Ukulele!",
                "trait": "jolly",
                "value": 3
            }
        ]
    },
    {
        "text": "So did you have a nice day yesterday?",
        "options": [
            {
                "option": "I think I did have a nice day yesterday, it was quite enjoyable.",
                "trait": "calm",
                "value": 2
            },
            {
                "option": "I can't remember what I did yesterday.",
                "trait": "quirky",
                "value": 1
            },
            {
                "option": "I had a terrible day.",
                "trait": "neutral",
                "value": 2
            }
        ]
    },
    {
        "text": "If you missed the bus, how would you react?",
        "options": [
            {
                "option": "Who cares man, I don't need no education.",
                "trait": "jolly",
                "value": 2
            },
            {
                "option": "Time to get the bike out!",
                "trait": "hardy",
                "value": 1
            },
            {
                "option": "Unleash the rage on some other things!",
                "trait": "rash",
                "value": 3
            }
        ]
    },
    {
        "text": "Someone steals your backpack! You see the guy later on, what do you do?",
        "options": [
            {
                "option": "Grab your gang and take him out!",
                "trait": "rash",
                "value": 1
            },
            {
                "option": "Go tell a teacher!",
                "trait": "hardy",
                "value": 1
            },
            {
                "option": "Ask for it back.",
                "trait": "calm",
                "value": 0
            }
        ]
    },
    {
        "text": "Are you impressed with my programming magic?",
        "options": [
            {
                "option": "Yes, it is quite nice actually.",
                "value": 1
            },
            {
                "option": "Could be better.",
                "value": 0
            }
        ]
    },
    {
        "text": "What is your idea of a good time?",
        "options": [
            {
                "option": "Going out and having a rave party!",
                "trait": "jolly",
                "value": 2
            },
            {
                "option": "Having a barbecue with friends.",
                "trait": "calm",
                "value": 1
            },
            {
                "option": "Breaking that new squat PR at the gym with my bros!!",
                "trait": "hardy",
                "value": 10
            },
            {
                "option": "Just sitting in the grass relaxing.",
                "trait": "calm",
                "value": 1
            }
        ]
    },
    {
        "text": "What is your favorite video game?",
        "options": [
            {
                "option": "Call of Duty!",
                "trait": "rash",
                "value": 2
            },
            {
                "option": "Minecraft.",
                "trait": "jolly",
                "value": 1
            },
            {
                "option": "Farmville!",
                "trait": "quirky",
                "value": 1
            }
        ]
    },
    {
        "text": "You're in the movies and someone keeps checking their phone and annoying everyone. What would you do?",
        "options": [
            {
                "option": "Throw some popcorn or a drink at them.",
                "trait": "rash",
                "value": 3
            },
            {
                "option": "Ignore them to keep the peace.",
                "trait": "calm",
                "value": 1
            },
            {
                "option": "Endure, for that is what you have always done.",
                "trait": "hardy",
                "value": 2
            }
        ]
    },
    {
        "text": "If you had to write a bunch of questions like I do now, how would you do it?",
        "options": [
            {
                "option": "Be lazy and don't do it like I've been doing for the last five months!",
                "trait": "jolly",
                "value": 1
            },
            {
                "option": "Do it all at once to get it over with.",
                "trait": "hardy",
                "value": 2
            },
            {
                "option": "Just write a program that will take a month to do that will make adding questions super easy!",
                "trait": "quirky",
                "value": 3
            },
            {
                "option": "^I wish, I wish.",
                "trait": "neutral",
                "value": 1
            }
        ]
    },
    {
        "text": "Did you have breakfast this morning?",
        "options": [
            {
                "option": "Yes.",
		     "trait": "calm",
                "value": 1
            },
            {
                "option": "No.",
		     "trait": "rash",
                "value": 2
            }
        ]
    },
    {
        "text": "If you were looking for a house, what kind of house would you get?",
        "options": [
            {
                "option": "A nice quaint house out in the woods.",
                "trait": "calm",
                "value": 1
            },
            {
                "option": "Something nice in the city for some prime real estate!",
                "trait": "rash",
                "value": 2
            },
            {
                "option": "I live in a cave.",
                "trait": "quirky",
                "value": 1
            }
        ]
    },
    {
        "text": "You are writing essays for your college applications, how do you write them?",
        "options": [
            {
                "option": "Be honest about your faults and try to express your personality.",
                "trait": "calm",
                "value": 1
            },
            {
                "option": "Write a pun filled masterpiece!",
                "trait": "jolly",
                "value": 2
            },
            {
                "option": "Write the way you were told by your teachers to highlight your good character traits.",
                "value": 1
            }
        ]
    },
    {
        "text": "You have recently come into a large sum of money and your friend asks you for some. What do you do?",
        "options": [
            {
                "option": "Draft an agreement and have it notarized, dictating how much is given and how the money will be repaid.",
                "trait": "calm",
                "value": 3
            },
            {
                "option": "Just hand it over! It's your friend right?!",
                "trait": "rash",
                "value": 2
            },
            {
                "option": "Laugh in his face and spend it all for yourself.",
                "trait": "quirky",
                "value": 1
            }
        ]
    },
    {
        "text": "What is your favorite catchphrase?",
        "options": [
            {
                "option": "Believe it!",
                "trait": "rash",
                "value": 2
            },
            {
                "option": "Work hard. Play hard.!",
                "trait": "hardy",
                "value": 2
            },
            {
                "option": "I am Groot.",
                "trait": "quirky",
                "value": 1
            },
            {
                "option": "It's time to D-d-d-d-dddddddddddduel!",
                "trait": "quirky",
                "value": 3
            }
        ]
    }/*,
    {
        "text": "Are you impressed with my programming magic?",
        "options": [
            {
                "option": "Yes, it is quite nice actually.",
                "value": 1
            },
            {
                "option": "Could be better.",
                "value": 0
            }
        ]
    },
    {
        "text": "Are you impressed with my programming magic?",
        "options": [
            {
                "option": "Yes, it is quite nice actually.",
                "value": 1
            },
            {
                "option": "Could be better.",
                "value": 0
            }
        ]
    },
    {
        "text": "Are you impressed with my programming magic?",
        "options": [
            {
                "option": "Yes, it is quite nice actually.",
                "value": 1
            },
            {
                "option": "Could be better.",
                "value": 0
            }
        ]
    }*/
]
